{"id":"2e0e9f2e-32d9-4d4a-a451-918410d24f6b","timestamp":1762748540990,"matcher":{"static":{"/__nuxt_content/blog/sql_dump.txt":{"prerender":true},"/__nuxt_content/music/sql_dump.txt":{"prerender":true}},"wildcard":{"/blog":{"prerender":true}},"dynamic":{}},"prerendered":["/","/links","/about","/music","/blogall","/musicall","/music/bansanka","/music/nonjaeng","/music/a_priori","/music/slowly","/music/paradichlorobenzene","/blogall/버츄얼","/musicall/커미션","/blogall/작업실","/musicall/커버","/musicall/MR"]}